abx_plugin_chrome/__init__.py
abx_plugin_chrome/binaries.py
abx_plugin_chrome/config.py
abx_plugin_chrome/dom.py
abx_plugin_chrome/extract.js
abx_plugin_chrome/extractors.py
abx_plugin_chrome/pdf.py
abx_plugin_chrome/screenshot.py
abx_plugin_chrome-2024.10.28.dist-info/METADATA
abx_plugin_chrome-2024.10.28.dist-info/WHEEL
abx_plugin_chrome-2024.10.28.dist-info/entry_points.txt
abx_plugin_chrome-2024.10.28.dist-info/RECORD
